setup.cfg
setup.py
celery_geolocator/__init__.py
celery_geolocator/celery.py
celery_geolocator/config.py
celery_geolocator/geocoders.py
celery_geolocator/tasks.py
celery_geolocator.egg-info/PKG-INFO
celery_geolocator.egg-info/SOURCES.txt
celery_geolocator.egg-info/dependency_links.txt
celery_geolocator.egg-info/requires.txt
celery_geolocator.egg-info/top_level.txt
celery_geolocator/helpers/__init__.py
celery_geolocator/helpers/decorators.py
celery_geolocator/helpers/singleton.py
examples/__init__.py
examples/celeryconfig.py
examples/django_celery/__init__.py
examples/django_celery/manage.py
examples/django_celery/demoapp/__init__.py
examples/django_celery/demoapp/models.py
examples/django_celery/demoapp/tasks.py
examples/django_celery/demoapp/tests.py
examples/django_celery/demoapp/urls.py
examples/django_celery/demoapp/views.py
examples/django_celery/proj/__init__.py
examples/django_celery/proj/celery.py
examples/django_celery/proj/settings.py
examples/django_celery/proj/urls.py
examples/django_celery/proj/wsgi.py
examples/strait_celery/__init__.py
examples/strait_celery/test_celery_task.py