Metadata-Version: 1.1
Name: celery-geolocator
Version: 0.0.11
Summary: Celery Geolocator
Home-page: http://www.github.com/brentpayne/celery-geolocator
Author: Brent Payne
Author-email: brent.payne@gmail.com
License: UNKNOWN
Keywords: celery,geopy,geolocate,celery-geolocator,geolocator,celery_geolocator
Platform: UNKNOWN
Classifier: Topic :: Text Processing :: General
Classifier: Topic :: Text Processing
Classifier: Programming Language :: Python
Classifier: Operating System :: OS Independent
Classifier: Intended Audience :: Developers
Classifier: License :: OSI Approved :: GNU Lesser General Public License v3 (LGPLv3)
Requires: celery
Requires: geopy
